mcp_query/__init__.py
mcp_query/mcp_query.py
mcp_query-0.1.0.dist-info/licenses/LICENSE
mcp_query-0.1.0.dist-info/METADATA
mcp_query-0.1.0.dist-info/WHEEL
mcp_query-0.1.0.dist-info/entry_points.txt
mcp_query-0.1.0.dist-info/top_level.txt
mcp_query-0.1.0.dist-info/RECORD
