Metadata-Version: 2.4
Name: mcp_query
Version: 0.1.0
Summary: A tool to query Context7 MCP server for documentation
Home-page: https://github.com/alvinveroy/mcp_query
Author: Alvin Veroy
Author-email: me@alvin.tech
Classifier: Programming Language :: Python :: 3
Classifier: License :: OSI Approved :: MIT License
Classifier: Operating System :: OS Independent
Requires-Python: >=3.6
License-File: LICENSE
Dynamic: author
Dynamic: author-email
Dynamic: classifier
Dynamic: description
Dynamic: description-content-type
Dynamic: home-page
Dynamic: license-file
Dynamic: requires-python
Dynamic: summary
